odoo/addons/sale_report_salesman/README.rst
odoo/addons/sale_report_salesman/__init__.py
odoo/addons/sale_report_salesman/__manifest__.py
odoo/addons/sale_report_salesman/hooks.py
odoo/addons/sale_report_salesman/i18n/es.po
odoo/addons/sale_report_salesman/i18n/it.po
odoo/addons/sale_report_salesman/i18n/sale_report_salesman.pot
odoo/addons/sale_report_salesman/readme/CONTRIBUTORS.md
odoo/addons/sale_report_salesman/readme/DESCRIPTION.md
odoo/addons/sale_report_salesman/static/description/icon.png
odoo/addons/sale_report_salesman/static/description/index.html
odoo/addons/sale_report_salesman/tests/__init__.py
odoo/addons/sale_report_salesman/tests/test_uninstall_hook.py
odoo/addons/sale_report_salesman/views/menu_views.xml
odoo_addon_sale_report_salesman-17.0.1.0.0.3.dist-info/METADATA
odoo_addon_sale_report_salesman-17.0.1.0.0.3.dist-info/WHEEL
odoo_addon_sale_report_salesman-17.0.1.0.0.3.dist-info/top_level.txt
odoo_addon_sale_report_salesman-17.0.1.0.0.3.dist-info/RECORD
